puzzle_generator/README.md
puzzle_generator/__init__.py
puzzle_generator/bu_configurators.py
puzzle_generator/bytes_utils.py
puzzle_generator/bytestr_utils_64.py
puzzle_generator/bytestr_utils_85.py
puzzle_generator/create_puzzle.py
puzzle_generator/ea_configurators/__init__.py
puzzle_generator/ea_configurators/check_kwargs.py
puzzle_generator/ea_configurators/ea_configurators.py
puzzle_generator/ea_configurators/eac_simple/__init__.py
puzzle_generator/ea_configurators/eac_simple/eacs_common.py
puzzle_generator/ea_configurators/eac_simple/eacs_simple.py
puzzle_generator/ea_configurators/eac_simple/eacs_spiced.py
puzzle_generator/encryption_algorithms/__init__.py
puzzle_generator/encryption_algorithms/ea_simple/__init__.py
puzzle_generator/encryption_algorithms/ea_simple/eas_common.py
puzzle_generator/encryption_algorithms/ea_simple/eas_simple.py
puzzle_generator/encryption_algorithms/ea_simple/eas_spiced.py
puzzle_generator/puzzle_data_creators.py
puzzle_generator/puzzle_data_encryption.py
puzzle_generator/rp_configurators.py
puzzle_generator/run_puzzle.py
puzzle_generator-0.17.1.dist-info/METADATA
puzzle_generator-0.17.1.dist-info/WHEEL
puzzle_generator-0.17.1.dist-info/licenses/LICENSE
puzzle_generator-0.17.1.dist-info/RECORD
