Metadata-Version: 2.4
Name: puzzle-generator
Version: 0.17.1
Summary: Generates python code representing a puzzle
License: MIT
License-File: LICENSE
Keywords: puzzle-generation,quiz-generation,code-generation
Author: piotr.idzik
Author-email: vil02_puzzle_generator@10g.pl
Requires-Python: >=3.10,<4.0.0
Classifier: License :: OSI Approved :: MIT License
Classifier: Programming Language :: Python :: 3
Classifier: Programming Language :: Python :: 3.10
Classifier: Programming Language :: Python :: 3.11
Classifier: Programming Language :: Python :: 3.12
Classifier: Programming Language :: Python :: 3.13
Classifier: Programming Language :: Python :: 3.14
Requires-Dist: black (==26.1.0)
Project-URL: Repository, https://github.com/vil02/puzzle_generator
